ip2domains/__init__.py
ip2domains/__main__.py
ip2domains-0.1.2.dist-info/METADATA
ip2domains-0.1.2.dist-info/WHEEL
ip2domains-0.1.2.dist-info/entry_points.txt
ip2domains-0.1.2.dist-info/RECORD
