Metadata-Version: 2.1
Name: ip2domains
Version: 0.1.2
Summary: Scans IP addresses and finds domains
Home-page: https://github.com/s3rgeym/ip2domains
Author: Sergey M
Requires-Python: >=3.11,<4.0
Classifier: Programming Language :: Python :: 3
Classifier: Programming Language :: Python :: 3.11
Project-URL: Repository, https://github.com/s3rgeym/ip2domains
